MANIFEST.in
setup.py
anymesh/__init__.py
anymesh/connections.py
anymesh.egg-info/PKG-INFO
anymesh.egg-info/SOURCES.txt
anymesh.egg-info/dependency_links.txt
anymesh.egg-info/not-zip-safe
anymesh.egg-info/requires.txt
anymesh.egg-info/top_level.txt