Metadata-Version: 1.0
Name: anymesh
Version: 0.4.0
Summary: AnyMesh is a multi-platform, decentralized, auto-discovery, auto-connect mesh networking API.
Home-page: https://github.com/AnyMesh/anyMesh-Python.git
Author: Dave Paul
Author-email: davepaul0@gmail.com
License: MIT
Platform: UNKNOWN
